<?xml version="1.0" encoding="utf-8"?>
<arch:spatialUnit xmlns:arch="http://ochre.lib.uchicago.edu/schema/SpatialUnit/SpatialUnit.xsd" xmlns:oc="http://opencontext.org/schema/space_schema_v1.xsd" xmlns:dc="http://purl.org/dc/elements/1.1/" xmlns:gml="http://www.opengis.net/gml" UUID="2EC9FEF5-8173-480D-DD71-71DD001FEDE6" ownedBy="D297CD29-50CA-4B2C-4A07-498ADF3AF487">
  <arch:name>
    <arch:string>Lot 713</arch:string>
  </arch:name>
  <oc:item_class>
    <oc:name>Lot</oc:name>
    <oc:iconURI>http://opencontext.org/database/ui_images/med_oc_icons/locus_lot_50x50.jpg</oc:iconURI>
  </oc:item_class>
  <arch:observations>
    <arch:observation obsNumber="1">
      <oc:obs_metadata>
        <oc:source>z_14_318b59136</oc:source>
      </oc:obs_metadata>
      <arch:properties>
        <arch:property>
          <arch:variableID>A1B35879-33D7-4B42-4778-D780BF13460B</arch:variableID>
          <arch:valueID>66B155D0-CAC0-46DE-5107-E13D7128C956</arch:valueID>
          <oc:propid href="http://opencontext.org/properties/B1EC3930-0E05-4E66-65EB-2889A8F57598">B1EC3930-0E05-4E66-65EB-2889A8F57598</oc:propid>
          <oc:var_label type="nominal">Square</oc:var_label>
          <oc:show_val>W1213</oc:show_val>
        </arch:property>
        <arch:property>
          <arch:variableID>EC2C9BC1-9CB3-4F3B-1DD6-B1C112E375FB</arch:variableID>
          <arch:valueID>DB7DEE85-4CC8-44F0-919E-CE406427E77E</arch:valueID>
          <oc:propid href="http://opencontext.org/properties/2CFC29A0-E3E0-469D-1E4D-C4ED62769700">2CFC29A0-E3E0-469D-1E4D-C4ED62769700</oc:propid>
          <oc:var_label type="nominal">Period</oc:var_label>
          <oc:show_val>IX</oc:show_val>
        </arch:property>
      </arch:properties>
      <arch:notes>
        <arch:note>
          <arch:string type="xhtml">
            <div xmlns="http://www.w3.org/1999/xhtml">This project primarily provided zooarchaeological data. The project dataset did not include extensive description of contexts. Some contexts may have repeating properties, indicating that the context identifiers provided to Open Context were probably not unique. The Open Context editorial staff was unable to resolve these identifier issues. Therefore, these context descriptions should be seen as provisional.</div>
          </arch:string>
        </arch:note>
      </arch:notes>
    </arch:observation>
  </arch:observations>
  <oc:context>
    <oc:tree id="default">
      <oc:parent href="http://opencontext.org/subjects/1_Global_Spatial">
        <oc:name>Turkey</oc:name>
        <oc:id>1_Global_Spatial</oc:id>
        <oc:level>3</oc:level>
        <oc:item_class>
          <oc:name>Region</oc:name>
          <oc:iconURI>http://opencontext.org/database/ui_images/med_oc_icons/region_30x30.jpg</oc:iconURI>
        </oc:item_class>
      </oc:parent>
      <oc:parent href="http://opencontext.org/subjects/59BF3CA5-014F-4A9C-047E-6256D11D4822">
        <oc:name>Ilıpınar</oc:name>
        <oc:id>59BF3CA5-014F-4A9C-047E-6256D11D4822</oc:id>
        <oc:level>2</oc:level>
        <oc:item_class>
          <oc:name>Site</oc:name>
          <oc:iconURI>http://opencontext.org/database/ui_images/med_oc_icons/site_30x30.jpg</oc:iconURI>
        </oc:item_class>
      </oc:parent>
      <oc:parent href="http://opencontext.org/subjects/A5F68881-CE0C-4EBD-CEBA-D511A05BE18B">
        <oc:name>Area 72</oc:name>
        <oc:id>A5F68881-CE0C-4EBD-CEBA-D511A05BE18B</oc:id>
        <oc:level>1</oc:level>
        <oc:item_class>
          <oc:name>Area</oc:name>
          <oc:iconURI>http://opencontext.org/database/ui_images/med_oc_icons/operation_area_30x30.jpg</oc:iconURI>
        </oc:item_class>
      </oc:parent>
    </oc:tree>
  </oc:context>
  <oc:children>
    <oc:tree id="default">
      <oc:child href="http://opencontext.org/subjects/F3213826-6FF0-4128-F1E5-396E272F43D5">
        <oc:name>Bone 14546</oc:name>
        <oc:id>F3213826-6FF0-4128-F1E5-396E272F43D5</oc:id>
        <oc:item_class>
          <oc:name>Animal Bone</oc:name>
          <oc:iconURI>http://opencontext.org/database/ui_images/med_oc_icons/animal_bone_30x30.jpg</oc:iconURI>
        </oc:item_class>
        <oc:descriptor>metacarpus 3+4</oc:descriptor>
      </oc:child>
      <oc:child href="http://opencontext.org/subjects/6E72DE35-E6B9-4704-B9F3-5F8922132B22">
        <oc:name>Bone 14547</oc:name>
        <oc:id>6E72DE35-E6B9-4704-B9F3-5F8922132B22</oc:id>
        <oc:item_class>
          <oc:name>Animal Bone</oc:name>
          <oc:iconURI>http://opencontext.org/database/ui_images/med_oc_icons/animal_bone_30x30.jpg</oc:iconURI>
        </oc:item_class>
        <oc:descriptor>antler</oc:descriptor>
      </oc:child>
      <oc:child href="http://opencontext.org/subjects/71DC3BBB-D3B3-4811-F6EB-FF4B5DDAAEAB">
        <oc:name>Bone 14548</oc:name>
        <oc:id>71DC3BBB-D3B3-4811-F6EB-FF4B5DDAAEAB</oc:id>
        <oc:item_class>
          <oc:name>Animal Bone</oc:name>
          <oc:iconURI>http://opencontext.org/database/ui_images/med_oc_icons/animal_bone_30x30.jpg</oc:iconURI>
        </oc:item_class>
        <oc:descriptor>costae</oc:descriptor>
      </oc:child>
      <oc:child href="http://opencontext.org/subjects/FACAD488-554A-45E8-54D0-35C9BAC1DA20">
        <oc:name>Bone 14549</oc:name>
        <oc:id>FACAD488-554A-45E8-54D0-35C9BAC1DA20</oc:id>
        <oc:item_class>
          <oc:name>Animal Bone</oc:name>
          <oc:iconURI>http://opencontext.org/database/ui_images/med_oc_icons/animal_bone_30x30.jpg</oc:iconURI>
        </oc:item_class>
        <oc:descriptor>cranium</oc:descriptor>
      </oc:child>
      <oc:child href="http://opencontext.org/subjects/256FFB7C-98AA-438D-C05B-980FEDA8F9CD">
        <oc:name>Bone 14550</oc:name>
        <oc:id>256FFB7C-98AA-438D-C05B-980FEDA8F9CD</oc:id>
        <oc:item_class>
          <oc:name>Animal Bone</oc:name>
          <oc:iconURI>http://opencontext.org/database/ui_images/med_oc_icons/animal_bone_30x30.jpg</oc:iconURI>
        </oc:item_class>
        <oc:descriptor>fragment, long bone</oc:descriptor>
      </oc:child>
      <oc:child href="http://opencontext.org/subjects/583FC935-E65F-4C67-7419-79796706A8D7">
        <oc:name>Bone 14551</oc:name>
        <oc:id>583FC935-E65F-4C67-7419-79796706A8D7</oc:id>
        <oc:item_class>
          <oc:name>Animal Bone</oc:name>
          <oc:iconURI>http://opencontext.org/database/ui_images/med_oc_icons/animal_bone_30x30.jpg</oc:iconURI>
        </oc:item_class>
        <oc:descriptor>vertebra, lumbar</oc:descriptor>
      </oc:child>
      <oc:child href="http://opencontext.org/subjects/E653B0AE-DD2C-40B6-B2B6-44DEF44FD6E5">
        <oc:name>Bone 14552</oc:name>
        <oc:id>E653B0AE-DD2C-40B6-B2B6-44DEF44FD6E5</oc:id>
        <oc:item_class>
          <oc:name>Animal Bone</oc:name>
          <oc:iconURI>http://opencontext.org/database/ui_images/med_oc_icons/animal_bone_30x30.jpg</oc:iconURI>
        </oc:item_class>
        <oc:descriptor>costae</oc:descriptor>
      </oc:child>
      <oc:child href="http://opencontext.org/subjects/543DF65B-A0F3-4CAC-234C-5AC9050511B9">
        <oc:name>Bone 14553</oc:name>
        <oc:id>543DF65B-A0F3-4CAC-234C-5AC9050511B9</oc:id>
        <oc:item_class>
          <oc:name>Animal Bone</oc:name>
          <oc:iconURI>http://opencontext.org/database/ui_images/med_oc_icons/animal_bone_30x30.jpg</oc:iconURI>
        </oc:item_class>
        <oc:descriptor>costae</oc:descriptor>
      </oc:child>
      <oc:child href="http://opencontext.org/subjects/D871C32D-6D1A-492D-3865-71E9BA624896">
        <oc:name>Bone 14554</oc:name>
        <oc:id>D871C32D-6D1A-492D-3865-71E9BA624896</oc:id>
        <oc:item_class>
          <oc:name>Animal Bone</oc:name>
          <oc:iconURI>http://opencontext.org/database/ui_images/med_oc_icons/animal_bone_30x30.jpg</oc:iconURI>
        </oc:item_class>
        <oc:descriptor>fragment, long bone</oc:descriptor>
      </oc:child>
      <oc:child href="http://opencontext.org/subjects/0344F7A2-5201-49D1-6398-1D52C96D53AE">
        <oc:name>Bone 14555</oc:name>
        <oc:id>0344F7A2-5201-49D1-6398-1D52C96D53AE</oc:id>
        <oc:item_class>
          <oc:name>Animal Bone</oc:name>
          <oc:iconURI>http://opencontext.org/database/ui_images/med_oc_icons/animal_bone_30x30.jpg</oc:iconURI>
        </oc:item_class>
        <oc:descriptor>vertebra, lumbar</oc:descriptor>
      </oc:child>
      <oc:child href="http://opencontext.org/subjects/FD8096B3-6E3E-402A-8013-CC73A2AD66D2">
        <oc:name>Bone 14556</oc:name>
        <oc:id>FD8096B3-6E3E-402A-8013-CC73A2AD66D2</oc:id>
        <oc:item_class>
          <oc:name>Animal Bone</oc:name>
          <oc:iconURI>http://opencontext.org/database/ui_images/med_oc_icons/animal_bone_30x30.jpg</oc:iconURI>
        </oc:item_class>
        <oc:descriptor>fragment, long bone</oc:descriptor>
      </oc:child>
      <oc:child href="http://opencontext.org/subjects/97A47389-FD1D-48C1-9965-E546C0B0099E">
        <oc:name>Bone 14557</oc:name>
        <oc:id>97A47389-FD1D-48C1-9965-E546C0B0099E</oc:id>
        <oc:item_class>
          <oc:name>Animal Bone</oc:name>
          <oc:iconURI>http://opencontext.org/database/ui_images/med_oc_icons/animal_bone_30x30.jpg</oc:iconURI>
        </oc:item_class>
        <oc:descriptor>fragment, long bone</oc:descriptor>
      </oc:child>
      <oc:child href="http://opencontext.org/subjects/39EAB549-5F80-400C-566C-5C74E438A602">
        <oc:name>Bone 14558</oc:name>
        <oc:id>39EAB549-5F80-400C-566C-5C74E438A602</oc:id>
        <oc:item_class>
          <oc:name>Animal Bone</oc:name>
          <oc:iconURI>http://opencontext.org/database/ui_images/med_oc_icons/animal_bone_30x30.jpg</oc:iconURI>
        </oc:item_class>
        <oc:descriptor>vertebra, caudal</oc:descriptor>
      </oc:child>
      <oc:child href="http://opencontext.org/subjects/8E87BC97-3DC5-4775-C99F-04D368C52F0F">
        <oc:name>Bone 14559</oc:name>
        <oc:id>8E87BC97-3DC5-4775-C99F-04D368C52F0F</oc:id>
        <oc:item_class>
          <oc:name>Animal Bone</oc:name>
          <oc:iconURI>http://opencontext.org/database/ui_images/med_oc_icons/animal_bone_30x30.jpg</oc:iconURI>
        </oc:item_class>
        <oc:descriptor>vertebra, unidentified</oc:descriptor>
      </oc:child>
      <oc:child href="http://opencontext.org/subjects/920B9699-F017-4C9A-1143-294D56AF716D">
        <oc:name>Bone 14560</oc:name>
        <oc:id>920B9699-F017-4C9A-1143-294D56AF716D</oc:id>
        <oc:item_class>
          <oc:name>Animal Bone</oc:name>
          <oc:iconURI>http://opencontext.org/database/ui_images/med_oc_icons/animal_bone_30x30.jpg</oc:iconURI>
        </oc:item_class>
        <oc:descriptor>costae</oc:descriptor>
      </oc:child>
      <oc:child href="http://opencontext.org/subjects/A3696B92-A60A-4684-A4FA-2C96A076B341">
        <oc:name>Bone 14561</oc:name>
        <oc:id>A3696B92-A60A-4684-A4FA-2C96A076B341</oc:id>
        <oc:item_class>
          <oc:name>Animal Bone</oc:name>
          <oc:iconURI>http://opencontext.org/database/ui_images/med_oc_icons/animal_bone_30x30.jpg</oc:iconURI>
        </oc:item_class>
        <oc:descriptor>cranium</oc:descriptor>
      </oc:child>
      <oc:child href="http://opencontext.org/subjects/2BEF082F-1DF5-4392-93B0-9726C06EED60">
        <oc:name>Bone 14562</oc:name>
        <oc:id>2BEF082F-1DF5-4392-93B0-9726C06EED60</oc:id>
        <oc:item_class>
          <oc:name>Animal Bone</oc:name>
          <oc:iconURI>http://opencontext.org/database/ui_images/med_oc_icons/animal_bone_30x30.jpg</oc:iconURI>
        </oc:item_class>
        <oc:descriptor>mandibula</oc:descriptor>
      </oc:child>
      <oc:child href="http://opencontext.org/subjects/3C65EA9D-7373-4269-DBE8-A6B64815B2A9">
        <oc:name>Bone 14563</oc:name>
        <oc:id>3C65EA9D-7373-4269-DBE8-A6B64815B2A9</oc:id>
        <oc:item_class>
          <oc:name>Animal Bone</oc:name>
          <oc:iconURI>http://opencontext.org/database/ui_images/med_oc_icons/animal_bone_30x30.jpg</oc:iconURI>
        </oc:item_class>
        <oc:descriptor>scapula</oc:descriptor>
      </oc:child>
      <oc:child href="http://opencontext.org/subjects/54449738-4A55-4464-5CFA-2AA3780A2BE9">
        <oc:name>Bone 14564</oc:name>
        <oc:id>54449738-4A55-4464-5CFA-2AA3780A2BE9</oc:id>
        <oc:item_class>
          <oc:name>Animal Bone</oc:name>
          <oc:iconURI>http://opencontext.org/database/ui_images/med_oc_icons/animal_bone_30x30.jpg</oc:iconURI>
        </oc:item_class>
        <oc:descriptor>pelvis</oc:descriptor>
      </oc:child>
      <oc:child href="http://opencontext.org/subjects/5A1A5CD4-737E-4F1F-091B-D4B71A0E615F">
        <oc:name>Bone 14565</oc:name>
        <oc:id>5A1A5CD4-737E-4F1F-091B-D4B71A0E615F</oc:id>
        <oc:item_class>
          <oc:name>Animal Bone</oc:name>
          <oc:iconURI>http://opencontext.org/database/ui_images/med_oc_icons/animal_bone_30x30.jpg</oc:iconURI>
        </oc:item_class>
        <oc:descriptor>phalanx II</oc:descriptor>
      </oc:child>
      <oc:child href="http://opencontext.org/subjects/0FEB8986-6948-4D08-F92D-A04969F68BC5">
        <oc:name>Bone 14566</oc:name>
        <oc:id>0FEB8986-6948-4D08-F92D-A04969F68BC5</oc:id>
        <oc:item_class>
          <oc:name>Animal Bone</oc:name>
          <oc:iconURI>http://opencontext.org/database/ui_images/med_oc_icons/animal_bone_30x30.jpg</oc:iconURI>
        </oc:item_class>
        <oc:descriptor>scapula</oc:descriptor>
      </oc:child>
      <oc:child href="http://opencontext.org/subjects/442061D1-35B7-4F2B-0FB2-4EB1FE1547B1">
        <oc:name>Bone 14567</oc:name>
        <oc:id>442061D1-35B7-4F2B-0FB2-4EB1FE1547B1</oc:id>
        <oc:item_class>
          <oc:name>Animal Bone</oc:name>
          <oc:iconURI>http://opencontext.org/database/ui_images/med_oc_icons/animal_bone_30x30.jpg</oc:iconURI>
        </oc:item_class>
        <oc:descriptor>horncore</oc:descriptor>
      </oc:child>
      <oc:child href="http://opencontext.org/subjects/EFD78107-80BD-4B6E-5FA8-4798BD4D78B3">
        <oc:name>Bone 14568</oc:name>
        <oc:id>EFD78107-80BD-4B6E-5FA8-4798BD4D78B3</oc:id>
        <oc:item_class>
          <oc:name>Animal Bone</oc:name>
          <oc:iconURI>http://opencontext.org/database/ui_images/med_oc_icons/animal_bone_30x30.jpg</oc:iconURI>
        </oc:item_class>
        <oc:descriptor>horncore + cranium</oc:descriptor>
      </oc:child>
      <oc:child href="http://opencontext.org/subjects/34364E66-5C82-49D2-51C7-24B35FC61A15">
        <oc:name>Bone 14569</oc:name>
        <oc:id>34364E66-5C82-49D2-51C7-24B35FC61A15</oc:id>
        <oc:item_class>
          <oc:name>Animal Bone</oc:name>
          <oc:iconURI>http://opencontext.org/database/ui_images/med_oc_icons/animal_bone_30x30.jpg</oc:iconURI>
        </oc:item_class>
        <oc:descriptor>tibia</oc:descriptor>
      </oc:child>
      <oc:child href="http://opencontext.org/subjects/672E52F2-669F-4766-455E-CBE70FBF662D">
        <oc:name>Bone 14570</oc:name>
        <oc:id>672E52F2-669F-4766-455E-CBE70FBF662D</oc:id>
        <oc:item_class>
          <oc:name>Animal Bone</oc:name>
          <oc:iconURI>http://opencontext.org/database/ui_images/med_oc_icons/animal_bone_30x30.jpg</oc:iconURI>
        </oc:item_class>
        <oc:descriptor>maxilla</oc:descriptor>
      </oc:child>
      <oc:child href="http://opencontext.org/subjects/632379F4-408D-40B7-DB09-99938809A22C">
        <oc:name>Bone 14571</oc:name>
        <oc:id>632379F4-408D-40B7-DB09-99938809A22C</oc:id>
        <oc:item_class>
          <oc:name>Animal Bone</oc:name>
          <oc:iconURI>http://opencontext.org/database/ui_images/med_oc_icons/animal_bone_30x30.jpg</oc:iconURI>
        </oc:item_class>
        <oc:descriptor>mandibula</oc:descriptor>
      </oc:child>
      <oc:child href="http://opencontext.org/subjects/0F399E07-3596-45A6-9531-FFA6733CAB4F">
        <oc:name>Bone 14572</oc:name>
        <oc:id>0F399E07-3596-45A6-9531-FFA6733CAB4F</oc:id>
        <oc:item_class>
          <oc:name>Animal Bone</oc:name>
          <oc:iconURI>http://opencontext.org/database/ui_images/med_oc_icons/animal_bone_30x30.jpg</oc:iconURI>
        </oc:item_class>
        <oc:descriptor>mandibula</oc:descriptor>
      </oc:child>
      <oc:child href="http://opencontext.org/subjects/DE7B617C-41D5-47CD-16E7-E920A5F22A08">
        <oc:name>Bone 14573</oc:name>
        <oc:id>DE7B617C-41D5-47CD-16E7-E920A5F22A08</oc:id>
        <oc:item_class>
          <oc:name>Animal Bone</oc:name>
          <oc:iconURI>http://opencontext.org/database/ui_images/med_oc_icons/animal_bone_30x30.jpg</oc:iconURI>
        </oc:item_class>
        <oc:descriptor>mandibula</oc:descriptor>
      </oc:child>
      <oc:child href="http://opencontext.org/subjects/5EEE162B-03C5-474A-7AC1-5A1B4ED38504">
        <oc:name>Bone 14574</oc:name>
        <oc:id>5EEE162B-03C5-474A-7AC1-5A1B4ED38504</oc:id>
        <oc:item_class>
          <oc:name>Animal Bone</oc:name>
          <oc:iconURI>http://opencontext.org/database/ui_images/med_oc_icons/animal_bone_30x30.jpg</oc:iconURI>
        </oc:item_class>
        <oc:descriptor>pelvis</oc:descriptor>
      </oc:child>
      <oc:child href="http://opencontext.org/subjects/4E519B44-D5D2-45D2-3761-875D5BAB040B">
        <oc:name>Bone 14575</oc:name>
        <oc:id>4E519B44-D5D2-45D2-3761-875D5BAB040B</oc:id>
        <oc:item_class>
          <oc:name>Animal Bone</oc:name>
          <oc:iconURI>http://opencontext.org/database/ui_images/med_oc_icons/animal_bone_30x30.jpg</oc:iconURI>
        </oc:item_class>
        <oc:descriptor>tibia</oc:descriptor>
      </oc:child>
      <oc:child href="http://opencontext.org/subjects/2A6A24DD-DBBC-4833-5F7B-F3217EDCE446">
        <oc:name>Bone 14576</oc:name>
        <oc:id>2A6A24DD-DBBC-4833-5F7B-F3217EDCE446</oc:id>
        <oc:item_class>
          <oc:name>Animal Bone</oc:name>
          <oc:iconURI>http://opencontext.org/database/ui_images/med_oc_icons/animal_bone_30x30.jpg</oc:iconURI>
        </oc:item_class>
        <oc:descriptor>mandibula</oc:descriptor>
      </oc:child>
      <oc:child href="http://opencontext.org/subjects/CDE799AE-67C0-4D97-17DF-D1A1F6053042">
        <oc:name>Bone 14577</oc:name>
        <oc:id>CDE799AE-67C0-4D97-17DF-D1A1F6053042</oc:id>
        <oc:item_class>
          <oc:name>Animal Bone</oc:name>
          <oc:iconURI>http://opencontext.org/database/ui_images/med_oc_icons/animal_bone_30x30.jpg</oc:iconURI>
        </oc:item_class>
        <oc:descriptor>scapula</oc:descriptor>
      </oc:child>
      <oc:child href="http://opencontext.org/subjects/445B878C-1269-4EF3-4A1B-C87F5AA8D0F0">
        <oc:name>Bone 14578</oc:name>
        <oc:id>445B878C-1269-4EF3-4A1B-C87F5AA8D0F0</oc:id>
        <oc:item_class>
          <oc:name>Animal Bone</oc:name>
          <oc:iconURI>http://opencontext.org/database/ui_images/med_oc_icons/animal_bone_30x30.jpg</oc:iconURI>
        </oc:item_class>
        <oc:descriptor>os carpi or os tarsi</oc:descriptor>
      </oc:child>
      <oc:child href="http://opencontext.org/subjects/03AB2D63-E568-4BFD-5236-4487005B4829">
        <oc:name>Bone 14579</oc:name>
        <oc:id>03AB2D63-E568-4BFD-5236-4487005B4829</oc:id>
        <oc:item_class>
          <oc:name>Animal Bone</oc:name>
          <oc:iconURI>http://opencontext.org/database/ui_images/med_oc_icons/animal_bone_30x30.jpg</oc:iconURI>
        </oc:item_class>
        <oc:descriptor>astragalus</oc:descriptor>
      </oc:child>
      <oc:child href="http://opencontext.org/subjects/45F66FEF-A12F-4BF8-098F-0593F5CD74A2">
        <oc:name>Bone 14580</oc:name>
        <oc:id>45F66FEF-A12F-4BF8-098F-0593F5CD74A2</oc:id>
        <oc:item_class>
          <oc:name>Animal Bone</oc:name>
          <oc:iconURI>http://opencontext.org/database/ui_images/med_oc_icons/animal_bone_30x30.jpg</oc:iconURI>
        </oc:item_class>
        <oc:descriptor>metatarsus 3+4</oc:descriptor>
      </oc:child>
      <oc:child href="http://opencontext.org/subjects/F545699C-2539-4F2A-614C-2F3F9D1AC445">
        <oc:name>Bone 14581</oc:name>
        <oc:id>F545699C-2539-4F2A-614C-2F3F9D1AC445</oc:id>
        <oc:item_class>
          <oc:name>Animal Bone</oc:name>
          <oc:iconURI>http://opencontext.org/database/ui_images/med_oc_icons/animal_bone_30x30.jpg</oc:iconURI>
        </oc:item_class>
        <oc:descriptor>calcaneus</oc:descriptor>
      </oc:child>
      <oc:child href="http://opencontext.org/subjects/64EAEFFF-249C-403F-2A7D-22C61A2F0643">
        <oc:name>Bone 14582</oc:name>
        <oc:id>64EAEFFF-249C-403F-2A7D-22C61A2F0643</oc:id>
        <oc:item_class>
          <oc:name>Animal Bone</oc:name>
          <oc:iconURI>http://opencontext.org/database/ui_images/med_oc_icons/animal_bone_30x30.jpg</oc:iconURI>
        </oc:item_class>
        <oc:descriptor>antler</oc:descriptor>
      </oc:child>
      <oc:child href="http://opencontext.org/subjects/29A84AAF-43BC-4685-D583-1E9C01CE8F5B">
        <oc:name>Bone 14583</oc:name>
        <oc:id>29A84AAF-43BC-4685-D583-1E9C01CE8F5B</oc:id>
        <oc:item_class>
          <oc:name>Animal Bone</oc:name>
          <oc:iconURI>http://opencontext.org/database/ui_images/med_oc_icons/animal_bone_30x30.jpg</oc:iconURI>
        </oc:item_class>
        <oc:descriptor>cranium</oc:descriptor>
      </oc:child>
      <oc:child href="http://opencontext.org/subjects/0E6DAD32-6A03-48D8-540D-8AB333B82C5B">
        <oc:name>Bone 14584</oc:name>
        <oc:id>0E6DAD32-6A03-48D8-540D-8AB333B82C5B</oc:id>
        <oc:item_class>
          <oc:name>Animal Bone</oc:name>
          <oc:iconURI>http://opencontext.org/database/ui_images/med_oc_icons/animal_bone_30x30.jpg</oc:iconURI>
        </oc:item_class>
        <oc:descriptor>cranium</oc:descriptor>
      </oc:child>
      <oc:child href="http://opencontext.org/subjects/D0D74E86-9654-402D-A7DA-E89ECB5AA119">
        <oc:name>Bone 14585</oc:name>
        <oc:id>D0D74E86-9654-402D-A7DA-E89ECB5AA119</oc:id>
        <oc:item_class>
          <oc:name>Animal Bone</oc:name>
          <oc:iconURI>http://opencontext.org/database/ui_images/med_oc_icons/animal_bone_30x30.jpg</oc:iconURI>
        </oc:item_class>
        <oc:descriptor>mandibula</oc:descriptor>
      </oc:child>
      <oc:child href="http://opencontext.org/subjects/6DEF181D-0167-48B8-3D20-1991661E2291">
        <oc:name>Bone 14586</oc:name>
        <oc:id>6DEF181D-0167-48B8-3D20-1991661E2291</oc:id>
        <oc:item_class>
          <oc:name>Animal Bone</oc:name>
          <oc:iconURI>http://opencontext.org/database/ui_images/med_oc_icons/animal_bone_30x30.jpg</oc:iconURI>
        </oc:item_class>
        <oc:descriptor>mandibula</oc:descriptor>
      </oc:child>
      <oc:child href="http://opencontext.org/subjects/B3AF512D-69AB-470A-9794-0611AD625471">
        <oc:name>Bone 14587</oc:name>
        <oc:id>B3AF512D-69AB-470A-9794-0611AD625471</oc:id>
        <oc:item_class>
          <oc:name>Animal Bone</oc:name>
          <oc:iconURI>http://opencontext.org/database/ui_images/med_oc_icons/animal_bone_30x30.jpg</oc:iconURI>
        </oc:item_class>
        <oc:descriptor>pelvis</oc:descriptor>
      </oc:child>
      <oc:child href="http://opencontext.org/subjects/A9A02F88-E42D-4750-28C9-2DE88DC2F0C7">
        <oc:name>Bone 14588</oc:name>
        <oc:id>A9A02F88-E42D-4750-28C9-2DE88DC2F0C7</oc:id>
        <oc:item_class>
          <oc:name>Animal Bone</oc:name>
          <oc:iconURI>http://opencontext.org/database/ui_images/med_oc_icons/animal_bone_30x30.jpg</oc:iconURI>
        </oc:item_class>
        <oc:descriptor>phalanx I</oc:descriptor>
      </oc:child>
      <oc:child href="http://opencontext.org/subjects/39F9AA27-1D4A-472F-657F-2805B040A38C">
        <oc:name>Bone 14589</oc:name>
        <oc:id>39F9AA27-1D4A-472F-657F-2805B040A38C</oc:id>
        <oc:item_class>
          <oc:name>Animal Bone</oc:name>
          <oc:iconURI>http://opencontext.org/database/ui_images/med_oc_icons/animal_bone_30x30.jpg</oc:iconURI>
        </oc:item_class>
        <oc:descriptor>phalanx II</oc:descriptor>
      </oc:child>
      <oc:child href="http://opencontext.org/subjects/DC24FC5D-3592-4956-E88D-B4E41E3577E9">
        <oc:name>Bone 14590</oc:name>
        <oc:id>DC24FC5D-3592-4956-E88D-B4E41E3577E9</oc:id>
        <oc:item_class>
          <oc:name>Animal Bone</oc:name>
          <oc:iconURI>http://opencontext.org/database/ui_images/med_oc_icons/animal_bone_30x30.jpg</oc:iconURI>
        </oc:item_class>
        <oc:descriptor>tibia</oc:descriptor>
      </oc:child>
      <oc:child href="http://opencontext.org/subjects/4A7E422C-0525-49C0-3229-D82DD1A8488C">
        <oc:name>Bone 14591</oc:name>
        <oc:id>4A7E422C-0525-49C0-3229-D82DD1A8488C</oc:id>
        <oc:item_class>
          <oc:name>Animal Bone</oc:name>
          <oc:iconURI>http://opencontext.org/database/ui_images/med_oc_icons/animal_bone_30x30.jpg</oc:iconURI>
        </oc:item_class>
        <oc:descriptor>large (greater than one half) single shell with hinge</oc:descriptor>
      </oc:child>
      <oc:child href="http://opencontext.org/subjects/04B48F2B-C9C4-4315-DD06-B774C983B2D2">
        <oc:name>Bone 14592</oc:name>
        <oc:id>04B48F2B-C9C4-4315-DD06-B774C983B2D2</oc:id>
        <oc:item_class>
          <oc:name>Animal Bone</oc:name>
          <oc:iconURI>http://opencontext.org/database/ui_images/med_oc_icons/animal_bone_30x30.jpg</oc:iconURI>
        </oc:item_class>
        <oc:descriptor>large (greater than one half) single shell with hinge</oc:descriptor>
      </oc:child>
      <oc:child href="http://opencontext.org/subjects/53E7A8A0-204D-4F54-6473-744EC56B0458">
        <oc:name>Bone 14593</oc:name>
        <oc:id>53E7A8A0-204D-4F54-6473-744EC56B0458</oc:id>
        <oc:item_class>
          <oc:name>Animal Bone</oc:name>
          <oc:iconURI>http://opencontext.org/database/ui_images/med_oc_icons/animal_bone_30x30.jpg</oc:iconURI>
        </oc:item_class>
        <oc:descriptor>small (less than one half) single shell with hinge</oc:descriptor>
      </oc:child>
      <oc:child href="http://opencontext.org/subjects/616F0919-239B-4A0A-136D-8B33DFC7621C">
        <oc:name>Bone 14594</oc:name>
        <oc:id>616F0919-239B-4A0A-136D-8B33DFC7621C</oc:id>
        <oc:item_class>
          <oc:name>Animal Bone</oc:name>
          <oc:iconURI>http://opencontext.org/database/ui_images/med_oc_icons/animal_bone_30x30.jpg</oc:iconURI>
        </oc:item_class>
        <oc:descriptor>small (less than one half) single shell with hinge</oc:descriptor>
      </oc:child>
      <oc:child href="http://opencontext.org/subjects/5456467F-48A1-484F-3439-D68F95EBF7C0">
        <oc:name>Bone 14595</oc:name>
        <oc:id>5456467F-48A1-484F-3439-D68F95EBF7C0</oc:id>
        <oc:item_class>
          <oc:name>Animal Bone</oc:name>
          <oc:iconURI>http://opencontext.org/database/ui_images/med_oc_icons/animal_bone_30x30.jpg</oc:iconURI>
        </oc:item_class>
        <oc:descriptor>small (less than one half) single shell without hinge</oc:descriptor>
      </oc:child>
      <oc:child href="http://opencontext.org/subjects/BC740A00-833D-4856-F6A3-2282FA71D68F">
        <oc:name>Bone 14596</oc:name>
        <oc:id>BC740A00-833D-4856-F6A3-2282FA71D68F</oc:id>
        <oc:item_class>
          <oc:name>Animal Bone</oc:name>
          <oc:iconURI>http://opencontext.org/database/ui_images/med_oc_icons/animal_bone_30x30.jpg</oc:iconURI>
        </oc:item_class>
        <oc:descriptor>large (greater than one half) single shell with hinge</oc:descriptor>
      </oc:child>
      <oc:child href="http://opencontext.org/subjects/8B098CD1-7766-410D-9D55-F55FF3B7EA16">
        <oc:name>Bone 36892</oc:name>
        <oc:id>8B098CD1-7766-410D-9D55-F55FF3B7EA16</oc:id>
        <oc:item_class>
          <oc:name>Animal Bone</oc:name>
          <oc:iconURI>http://opencontext.org/database/ui_images/med_oc_icons/animal_bone_30x30.jpg</oc:iconURI>
        </oc:item_class>
        <oc:descriptor>maxilla</oc:descriptor>
      </oc:child>
    </oc:tree>
  </oc:children>
  <oc:metadata>
    <dc:title>Ilıpınar Zooarchaeology: Lot 713 (Lot)</dc:title>
    <dc:publisher>Open Context</dc:publisher>
    <dc:date>2013-08-12</dc:date>
    <dc:subject>Neolithic</dc:subject>
    <dc:subject>Late Chalcolithic</dc:subject>
    <dc:subject>Early Bronze Age</dc:subject>
    <dc:subject>eastern Aegean</dc:subject>
    <dc:subject>western Anatolia</dc:subject>
    <dc:subject>zooarchaeology</dc:subject>
    <dc:subject>Faunal data</dc:subject>
    <dc:subject>Mammal Remains</dc:subject>
    <dc:subject/>
    <dc:creator href="http://opencontext.org/persons/93ECDD49-55C2-4404-4B93-490E925FC23E">Hijkle Buitenhuis</dc:creator>
    <dc:identifier>http://opencontext.org/subjects/2EC9FEF5-8173-480D-DD71-71DD001FEDE6</dc:identifier>
    <oc:project_name href="http://opencontext.org/projects/D297CD29-50CA-4B2C-4A07-498ADF3AF487">Ilıpınar Zooarchaeology</oc:project_name>
    <oc:pub_date>2013-08-12T00:00:00-07:00</oc:pub_date>
    <oc:coins>ctx_ver=Z39.88-2004&amp;rft_val_fmt=info%3Aofi%2Ffmt%3Akev%3Amtx%3Adc&amp;rft_val_fmt=info%3Aofi%2Ffmt%3Akev%3Amtx%3Adc&amp;rft.type=dataset&amp;rft.title=Il%C4%B1p%C4%B1nar+Zooarchaeology%3A+Lot+713+%28Lot%29&amp;rft.publisher=Open+Context&amp;rft.source=Open+Context&amp;rft.subject=Neolithic&amp;rft.subject=Late+Chalcolithic&amp;rft.subject=Early+Bronze+Age&amp;rft.subject=eastern+Aegean&amp;rft.subject=western+Anatolia&amp;rft.subject=zooarchaeology&amp;rft.subject=Faunal+data&amp;rft.subject=Mammal+Remains&amp;rft.subject=&amp;rft.creator=Hijkle+Buitenhuis&amp;rft.identifier=http%3A%2F%2Fopencontext.org%2Fsubjects%2F2EC9FEF5-8173-480D-DD71-71DD001FEDE6</oc:coins>
    <oc:geo_reference>
      <oc:geo_lat>40.468303</oc:geo_lat>
      <oc:geo_long>29.309099</oc:geo_long>
      <oc:metasource ref_type="contained" href="http://opencontext.org/subjects/59BF3CA5-014F-4A9C-047E-6256D11D4822">
        <oc:source_name>Ilıpınar</oc:source_name>
        <oc:source_id>59BF3CA5-014F-4A9C-047E-6256D11D4822</oc:source_id>
      </oc:metasource>
    </oc:geo_reference>
    <oc:copyright_lic href="http://creativecommons.org/licenses/by/3.0">
      <oc:lic_name>Attribution</oc:lic_name>
      <oc:lic_vers>3</oc:lic_vers>
      <oc:lic_URI>http://creativecommons.org/licenses/by/3.0</oc:lic_URI>
      <oc:lic_icon_URI>http://i.creativecommons.org/l/by/3.0/88x31.png</oc:lic_icon_URI>
    </oc:copyright_lic>
  </oc:metadata>
  <oc:social_usage>
    <oc:last_updated>2013-08-13T08:36:38-07:00</oc:last_updated>
    <oc:item_views>
      <oc:count>1</oc:count>
      <oc:view_time>2013/08/13 08:36:38</oc:view_time>
    </oc:item_views>
    <oc:user_tags>
      <oc:tag type="chronological" status="public">
        <oc:name>(6200 BCE - 5400 BCE)</oc:name>
        <oc:chrono isDuration="true">
          <oc:time_start>-6200</oc:time_start>
          <oc:time_finish>-5400</oc:time_finish>
          <oc:metasource ref_type="contained" href="http://opencontext.org/subjects/59BF3CA5-014F-4A9C-047E-6256D11D4822">
            <oc:source_name>Ilıpınar</oc:source_name>
            <oc:source_id>59BF3CA5-014F-4A9C-047E-6256D11D4822</oc:source_id>
          </oc:metasource>
        </oc:chrono>
        <oc:tag_creator id="oc">
          <oc:creator_name>Open Context Editors</oc:creator_name>
          <oc:set_label>Default set</oc:set_label>
          <oc:set_id>Default set</oc:set_id>
          <oc:set_date>2013-03-05T14:25:24-07:00</oc:set_date>
        </oc:tag_creator>
      </oc:tag>
    </oc:user_tags>
  </oc:social_usage>
</arch:spatialUnit>
